dataframe_service-0.1.13.data/scripts/dfs_cli
dataframe_service-0.1.13.data/scripts/dfs_server
dfs/__init__.py
dfs/df_cache.py
dfs/df_client.py
dfs/df_server.py
dfs/file_cache.py
dfs/helpers.py
dataframe_service-0.1.13.dist-info/METADATA
dataframe_service-0.1.13.dist-info/WHEEL
dataframe_service-0.1.13.dist-info/top_level.txt
dataframe_service-0.1.13.dist-info/RECORD
