Metadata-Version: 2.1
Name: dataframe-service
Version: 0.1.13
Summary: Pandas DataFrame Service (DFS).
Author: Brian Guarraci
License: MIT
Classifier: Programming Language :: Python :: 3
Classifier: License :: OSI Approved :: MIT License
Requires-Python: >=3.8
Requires-Dist: pandas (~=1.5.1)
Requires-Dist: pysimdjson (~=5.0.2)
Requires-Dist: colorama
